{"GlobalPropertiesHash":"kcI0i+SgAVDKy4nezQXSWZASND1SrvxtATUXhyyexJk=","FingerprintPatternsHash":"gq3WsqcKBUGTSNle7RKKyXRIwh7M8ccEqOqYvIzoM04=","PropertyOverridesHash":"8ZRc1sGeVrPBx4lD717BgRaQekyh78QKV9SKsdt638U=","InputHashes":["Qs2y8Xp5VC6Zwj/rI0kdu9hIPc2mTBBMvYkjhB9SSlw=","\u002BFDgIxZYggDtojd8JP/4yAovO0na22NXY6ept8SAXTA=","12Alqi2N3NXpfrFuRtBcuYZsRaVB5DzLALlIhblU6hQ=","Htde7IXHe6Y60oAGc3TGOfVfs0q783I/xtOL2KJaxEE=","FdFuXH6gK\u002BHhDfnUdYT5Vx8q7NWy5FWqjG1PTjBxtX8=","PtvTMCE\u002BeszMO0rv8C9TPjdi2W\u002BYjrvWWqbiIdxPHt4=","iCz9kwxbK48DzpLzufDOme4DmgDZ5mL/9nefjdgORdo="],"CachedAssets":{"Qs2y8Xp5VC6Zwj/rI0kdu9hIPc2mTBBMvYkjhB9SSlw=":{"Identity":"E:\\Projects\\Kanzie\\server\\Kanzie.Api\\wwwroot\\uploads\\24d302f3-65ba-4662-8ab7-785e8bde3f85","SourceId":"Kanzie.Api","SourceType":"Discovered","ContentRoot":"E:\\Projects\\Kanzie\\server\\Kanzie.Api\\wwwroot\\","BasePath":"_content/Kanzie.Api","RelativePath":"uploads/24d302f3-65ba-4662-8ab7-785e8bde3f85#[.{fingerprint}]?","AssetKind":"All","AssetMode":"All","AssetRole":"Primary","AssetMergeBehavior":null,"AssetMergeSource":"","RelatedAsset":null,"AssetTraitName":null,"AssetTraitValue":null,"Fingerprint":"4okb5mhl3b","Integrity":"ZMpMgXVctGhUFS23tDbM1g8KsCweVGIM9cKRlRYbcbE=","CopyToOutputDirectory":"Never","CopyToPublishDirectory":"PreserveNewest","OriginalItemSpec":"wwwroot\\uploads\\24d302f3-65ba-4662-8ab7-785e8bde3f85","FileLength":403191,"LastWriteTime":"2026-01-30T16:57:12.5338836+00:00"},"\u002BFDgIxZYggDtojd8JP/4yAovO0na22NXY6ept8SAXTA=":{"Identity":"E:\\Projects\\Kanzie\\server\\Kanzie.Api\\wwwroot\\uploads\\50347164-392d-47bf-851f-8c0b755fd402","SourceId":"Kanzie.Api","SourceType":"Discovered","ContentRoot":"E:\\Projects\\Kanzie\\server\\Kanzie.Api\\wwwroot\\","BasePath":"_content/Kanzie.Api","RelativePath":"uploads/50347164-392d-47bf-851f-8c0b755fd402#[.{fingerprint}]?","AssetKind":"All","AssetMode":"All","AssetRole":"Primary","AssetMergeBehavior":null,"AssetMergeSource":"","RelatedAsset":null,"AssetTraitName":null,"AssetTraitValue":null,"Fingerprint":"269aa1rekf","Integrity":"FpW/54PvaLy\u002BdN8WtEf6EvWsa96qv63Q4dTiT6NOzQQ=","CopyToOutputDirectory":"Never","CopyToPublishDirectory":"PreserveNewest","OriginalItemSpec":"wwwroot\\uploads\\50347164-392d-47bf-851f-8c0b755fd402","FileLength":1515675,"LastWriteTime":"2026-01-30T16:54:33.2646965+00:00"},"Htde7IXHe6Y60oAGc3TGOfVfs0q783I/xtOL2KJaxEE=":{"Identity":"E:\\Projects\\Kanzie\\server\\Kanzie.Api\\wwwroot\\uploads\\da7cfd93-c3ca-47c7-ba5d-e1d19d4ee995","SourceId":"Kanzie.Api","SourceType":"Discovered","ContentRoot":"E:\\Projects\\Kanzie\\server\\Kanzie.Api\\wwwroot\\","BasePath":"_content/Kanzie.Api","RelativePath":"uploads/da7cfd93-c3ca-47c7-ba5d-e1d19d4ee995#[.{fingerprint}]?","AssetKind":"All","AssetMode":"All","AssetRole":"Primary","AssetMergeBehavior":null,"AssetMergeSource":"","RelatedAsset":null,"AssetTraitName":null,"AssetTraitValue":null,"Fingerprint":"269aa1rekf","Integrity":"FpW/54PvaLy\u002BdN8WtEf6EvWsa96qv63Q4dTiT6NOzQQ=","CopyToOutputDirectory":"Never","CopyToPublishDirectory":"PreserveNewest","OriginalItemSpec":"wwwroot\\uploads\\da7cfd93-c3ca-47c7-ba5d-e1d19d4ee995","FileLength":1515675,"LastWriteTime":"2026-01-30T16:56:48.2151817+00:00"},"FdFuXH6gK\u002BHhDfnUdYT5Vx8q7NWy5FWqjG1PTjBxtX8=":{"Identity":"E:\\Projects\\Kanzie\\server\\Kanzie.Api\\wwwroot\\uploads\\fa5a2339-ad79-4cb1-97a6-923c38ee13c7.jpg","SourceId":"Kanzie.Api","SourceType":"Discovered","ContentRoot":"E:\\Projects\\Kanzie\\server\\Kanzie.Api\\wwwroot\\","BasePath":"_content/Kanzie.Api","RelativePath":"uploads/fa5a2339-ad79-4cb1-97a6-923c38ee13c7#[.{fingerprint}]?.jpg","AssetKind":"All","AssetMode":"All","AssetRole":"Primary","AssetMergeBehavior":null,"AssetMergeSource":"","RelatedAsset":null,"AssetTraitName":null,"AssetTraitValue":null,"Fingerprint":"269aa1rekf","Integrity":"FpW/54PvaLy\u002BdN8WtEf6EvWsa96qv63Q4dTiT6NOzQQ=","CopyToOutputDirectory":"Never","CopyToPublishDirectory":"PreserveNewest","OriginalItemSpec":"wwwroot\\uploads\\fa5a2339-ad79-4cb1-97a6-923c38ee13c7.jpg","FileLength":1515675,"LastWriteTime":"2026-01-30T17:00:57.3922596+00:00"},"12Alqi2N3NXpfrFuRtBcuYZsRaVB5DzLALlIhblU6hQ=":{"Identity":"E:\\Projects\\Kanzie\\server\\Kanzie.Api\\wwwroot\\uploads\\b88dea07-7ca8-4bcc-967b-8baea3fb1905.jpg","SourceId":"Kanzie.Api","SourceType":"Discovered","ContentRoot":"E:\\Projects\\Kanzie\\server\\Kanzie.Api\\wwwroot\\","BasePath":"_content/Kanzie.Api","RelativePath":"uploads/b88dea07-7ca8-4bcc-967b-8baea3fb1905#[.{fingerprint}]?.jpg","AssetKind":"All","AssetMode":"All","AssetRole":"Primary","AssetMergeBehavior":null,"AssetMergeSource":"","RelatedAsset":null,"AssetTraitName":null,"AssetTraitValue":null,"Fingerprint":"269aa1rekf","Integrity":"FpW/54PvaLy\u002BdN8WtEf6EvWsa96qv63Q4dTiT6NOzQQ=","CopyToOutputDirectory":"Never","CopyToPublishDirectory":"PreserveNewest","OriginalItemSpec":"wwwroot\\uploads\\b88dea07-7ca8-4bcc-967b-8baea3fb1905.jpg","FileLength":1515675,"LastWriteTime":"2026-01-30T18:33:00.1366995+00:00"}},"CachedCopyCandidates":{}}